[{"documentURL": "https://marketingisbs.marketing/", "frameId": "6ABFA60F277AEB7D86AD858E7D73D2FE", "hasUserGesture": false, "initiator": {"stack": {"callFrames": [{"columnNumber": 64, "functionName": "", "lineNumber": 6, "scriptId": "5", "url": "https://marketingisbs.marketing/"}, {"columnNumber": 2, "functionName": "", "lineNumber": 7, "scriptId": "5", "url": "https://marketingisbs.marketing/"}]}, "type": "script"}, "loaderId": "BC682C64B0D5F02E31CE5EA697E84EEA", "redirectHasExtraInfo": false, "request": {"headers": {"Referer": "https://marketingisbs.marketing/", "User-Agent": "Mozilla/5.0 (X11; Linux x86_64) AppleWebKit/537.36 (KHTML, like Gecko) HeadlessChrome/120.0.6099.109 Safari/537.36", "sec-ch-ua": "\"Not_A Brand\";v=\"8\", \"Chromium\";v=\"120\", \"HeadlessChrome\";v=\"120\"", "sec-ch-ua-mobile": "?0", "sec-ch-ua-platform": "\"Linux\""}, "initialPriority": "Low", "isSameSite": false, "method": "GET", "mixedContentType": "none", "referrerPolicy": "strict-origin-when-cross-origin", "url": "https://www.googletagmanager.com/gtm.js?id=GTM-NCZZ2T3Z"}, "requestId": "19186.6", "timestamp": 3046.591475, "type": "Script", "wallTime": 1703621857.259627},{"documentURL": "https://marketingisbs.marketing/", "frameId": "6ABFA60F277AEB7D86AD858E7D73D2FE", "hasUserGesture": false, "initiator": {"stack": {"callFrames": [{"columnNumber": 397, "functionName": "Kc", "lineNumber": 69, "scriptId": "8", "url": "https://www.googletagmanager.com/gtm.js?id=GTM-NCZZ2T3Z"}, {"columnNumber": 392, "functionName": "ku", "lineNumber": 345, "scriptId": "8", "url": "https://www.googletagmanager.com/gtm.js?id=GTM-NCZZ2T3Z"}, {"columnNumber": 9, "functionName": "wu", "lineNumber": 354, "scriptId": "8", "url": "https://www.googletagmanager.com/gtm.js?id=GTM-NCZZ2T3Z"}, {"columnNumber": 260, "functionName": "", "lineNumber": 356, "scriptId": "8", "url": "https://www.googletagmanager.com/gtm.js?id=GTM-NCZZ2T3Z"}, {"columnNumber": 17, "functionName": "zu", "lineNumber": 360, "scriptId": "8", "url": "https://www.googletagmanager.com/gtm.js?id=GTM-NCZZ2T3Z"}, {"columnNumber": 173, "functionName": "Au", "lineNumber": 356, "scriptId": "8", "url": "https://www.googletagmanager.com/gtm.js?id=GTM-NCZZ2T3Z"}, {"columnNumber": 120, "functionName": "e", "lineNumber": 443, "scriptId": "8", "url": "https://www.googletagmanager.com/gtm.js?id=GTM-NCZZ2T3Z"}, {"columnNumber": 226, "functionName": "", "lineNumber": 444, "scriptId": "8", "url": "https://www.googletagmanager.com/gtm.js?id=GTM-NCZZ2T3Z"}, {"columnNumber": 340, "functionName": "Qj", "lineNumber": 186, "scriptId": "8", "url": "https://www.googletagmanager.com/gtm.js?id=GTM-NCZZ2T3Z"}, {"columnNumber": 347, "functionName": "dk", "lineNumber": 189, "scriptId": "8", "url": "https://www.googletagmanager.com/gtm.js?id=GTM-NCZZ2T3Z"}, {"columnNumber": 112, "functionName": "KC", "lineNumber": 444, "scriptId": "8", "url": "https://www.googletagmanager.com/gtm.js?id=GTM-NCZZ2T3Z"}, {"columnNumber": 370, "functionName": "", "lineNumber": 513, "scriptId": "8", "url": "https://www.googletagmanager.com/gtm.js?id=GTM-NCZZ2T3Z"}, {"columnNumber": 198, "functionName": "yf", "lineNumber": 105, "scriptId": "8", "url": "https://www.googletagmanager.com/gtm.js?id=GTM-NCZZ2T3Z"}, {"columnNumber": 213, "functionName": "e", "lineNumber": 376, "scriptId": "8", "url": "https://www.googletagmanager.com/gtm.js?id=GTM-NCZZ2T3Z"}, {"columnNumber": 129, "functionName": "", "lineNumber": 56, "scriptId": "8", "url": "https://www.googletagmanager.com/gtm.js?id=GTM-NCZZ2T3Z"}, {"columnNumber": 407, "functionName": "", "lineNumber": 377, "scriptId": "8", "url": "https://www.googletagmanager.com/gtm.js?id=GTM-NCZZ2T3Z"}, {"columnNumber": 147, "functionName": "", "lineNumber": 377, "scriptId": "8", "url": "https://www.googletagmanager.com/gtm.js?id=GTM-NCZZ2T3Z"}, {"columnNumber": 624, "functionName": "Kw", "lineNumber": 379, "scriptId": "8", "url": "https://www.googletagmanager.com/gtm.js?id=GTM-NCZZ2T3Z"}, {"columnNumber": 191, "functionName": "Tw", "lineNumber": 384, "scriptId": "8", "url": "https://www.googletagmanager.com/gtm.js?id=GTM-NCZZ2T3Z"}, {"columnNumber": 271, "functionName": "Px", "lineNumber": 398, "scriptId": "8", "url": "https://www.googletagmanager.com/gtm.js?id=GTM-NCZZ2T3Z"}, {"columnNumber": 54, "functionName": "Sx", "lineNumber": 403, "scriptId": "8", "url": "https://www.googletagmanager.com/gtm.js?id=GTM-NCZZ2T3Z"}, {"columnNumber": 42, "functionName": "Ux", "lineNumber": 404, "scriptId": "8", "url": "https://www.googletagmanager.com/gtm.js?id=GTM-NCZZ2T3Z"}]}, "type": "script"}, "loaderId": "BC682C64B0D5F02E31CE5EA697E84EEA", "redirectHasExtraInfo": false, "request": {"headers": {"Referer": "https://marketingisbs.marketing/", "User-Agent": "Mozilla/5.0 (X11; Linux x86_64) AppleWebKit/537.36 (KHTML, like Gecko) HeadlessChrome/120.0.6099.109 Safari/537.36", "sec-ch-ua": "\"Not_A Brand\";v=\"8\", \"Chromium\";v=\"120\", \"HeadlessChrome\";v=\"120\"", "sec-ch-ua-mobile": "?0", "sec-ch-ua-platform": "\"Linux\""}, "initialPriority": "Low", "isSameSite": false, "method": "GET", "mixedContentType": "none", "referrerPolicy": "strict-origin-when-cross-origin", "url": "https://www.googleadservices.com/pagead/conversion/marketingisbs.marketing/?random=1703621857426&cv=11&fst=1703621857426&bg=ffffff&guid=ON&async=1&gtm=45He3bt0v9168766396&gcd=11l1l1l1l1&dma=0&u_w=800&u_h=600&url=https%3A%2F%2Fmarketingisbs.marketing%2F&label=marketingisbs.marketing&hn=www.googleadservices.com&frm=0&tiba=Hello%20there&value=0&bttype=purchase&auid=577895664.1703621857&uaa=x86&uab=64&uafvl=Not_A%2520Brand%3B8.0.0.0%7CChromium%3B120.0.6099.109%7CHeadlessChrome%3B120.0.6099.109&uamb=0&uap=Linux&uapv=6.2.0&uaw=0&rfmt=3&fmt=4"}, "requestId": "19186.16", "timestamp": 3046.792562, "type": "Script", "wallTime": 1703621857.451923},{"documentURL": "https://marketingisbs.marketing/", "frameId": "6ABFA60F277AEB7D86AD858E7D73D2FE", "hasUserGesture": false, "initiator": {"stack": {"callFrames": [{"columnNumber": 45, "functionName": "Uc", "lineNumber": 195, "scriptId": "9", "url": "https://www.googletagmanager.com/gtag/js?id=G-TXTTC83R0T"}, {"columnNumber": 494, "functionName": "JF", "lineNumber": 599, "scriptId": "9", "url": "https://www.googletagmanager.com/gtag/js?id=G-TXTTC83R0T"}, {"columnNumber": 192, "functionName": "KF", "lineNumber": 595, "scriptId": "9", "url": "https://www.googletagmanager.com/gtag/js?id=G-TXTTC83R0T"}, {"columnNumber": 176, "functionName": "MF.D", "lineNumber": 598, "scriptId": "9", "url": "https://www.googletagmanager.com/gtag/js?id=G-TXTTC83R0T"}, {"columnNumber": 78, "functionName": "MF.add", "lineNumber": 599, "scriptId": "9", "url": "https://www.googletagmanager.com/gtag/js?id=G-TXTTC83R0T"}, {"columnNumber": 334, "functionName": "aa.mj", "lineNumber": 619, "scriptId": "9", "url": "https://www.googletagmanager.com/gtag/js?id=G-TXTTC83R0T"}, {"columnNumber": 254, "functionName": "aa.Km", "lineNumber": 619, "scriptId": "9", "url": "https://www.googletagmanager.com/gtag/js?id=G-TXTTC83R0T"}, {"columnNumber": 120, "functionName": "", "lineNumber": 603, "scriptId": "9", "url": "https://www.googletagmanager.com/gtag/js?id=G-TXTTC83R0T"}, {"columnNumber": 340, "functionName": "Qj", "lineNumber": 317, "scriptId": "9", "url": "https://www.googletagmanager.com/gtag/js?id=G-TXTTC83R0T"}, {"columnNumber": 347, "functionName": "dk", "lineNumber": 320, "scriptId": "9", "url": "https://www.googletagmanager.com/gtag/js?id=G-TXTTC83R0T"}, {"columnNumber": 104, "functionName": "k", "lineNumber": 603, "scriptId": "9", "url": "https://www.googletagmanager.com/gtag/js?id=G-TXTTC83R0T"}, {"columnNumber": 167, "functionName": "c", "lineNumber": 367, "scriptId": "9", "url": "https://www.googletagmanager.com/gtag/js?id=G-TXTTC83R0T"}, {"columnNumber": 198, "functionName": "yn", "lineNumber": 367, "scriptId": "9", "url": "https://www.googletagmanager.com/gtag/js?id=G-TXTTC83R0T"}, {"columnNumber": 143, "functionName": "aa.Jm", "lineNumber": 603, "scriptId": "9", "url": "https://www.googletagmanager.com/gtag/js?id=G-TXTTC83R0T"}, {"columnNumber": 677, "functionName": "c", "lineNumber": 622, "scriptId": "9", "url": "https://www.googletagmanager.com/gtag/js?id=G-TXTTC83R0T"}, {"columnNumber": 297, "functionName": "nq", "lineNumber": 408, "scriptId": "9", "url": "https://www.googletagmanager.com/gtag/js?id=G-TXTTC83R0T"}, {"columnNumber": 94, "functionName": "mq.flush", "lineNumber": 411, "scriptId": "9", "url": "https://www.googletagmanager.com/gtag/js?id=G-TXTTC83R0T"}, {"columnNumber": 206, "functionName": "mq.push", "lineNumber": 409, "scriptId": "9", "url": "https://www.googletagmanager.com/gtag/js?id=G-TXTTC83R0T"}, {"columnNumber": 38, "functionName": "config", "lineNumber": 474, "scriptId": "9", "url": "https://www.googletagmanager.com/gtag/js?id=G-TXTTC83R0T"}, {"columnNumber": 471, "functionName": "Sx", "lineNumber": 485, "scriptId": "9", "url": "https://www.googletagmanager.com/gtag/js?id=G-TXTTC83R0T"}, {"columnNumber": 314, "functionName": "Wx.b.push", "lineNumber": 490, "scriptId": "9", "url": "https://www.googletagmanager.com/gtag/js?id=G-TXTTC83R0T"}, {"columnNumber": 302, "functionName": "", "lineNumber": 406, "scriptId": "8", "url": "https://www.googletagmanager.com/gtm.js?id=GTM-NCZZ2T3Z"}]}, "type": "script"}, "loaderId": "BC682C64B0D5F02E31CE5EA697E84EEA", "redirectHasExtraInfo": false, "request": {"hasPostData": true, "headers": {"Referer": "https://marketingisbs.marketing/", "User-Agent": "Mozilla/5.0 (X11; Linux x86_64) AppleWebKit/537.36 (KHTML, like Gecko) HeadlessChrome/120.0.6099.109 Safari/537.36", "sec-ch-ua": "\"Not_A Brand\";v=\"8\", \"Chromium\";v=\"120\", \"HeadlessChrome\";v=\"120\"", "sec-ch-ua-mobile": "?0", "sec-ch-ua-platform": "\"Linux\""}, "initialPriority": "VeryLow", "isSameSite": false, "method": "POST", "mixedContentType": "none", "postDataEntries": [{"bytes": ""}], "referrerPolicy": "strict-origin-when-cross-origin", "url": "https://analytics.google.com/g/collect?v=2&tid=G-TXTTC83R0T&gtm=45je3bt0v9169951526&_p=1703621857248&_gaz=1&gcd=11l1l1l1l1&dma=0&cid=1381979668.1703621857&ul=en-us&sr=800x600&uaa=x86&uab=64&uafvl=Not_A%2520Brand%3B8.0.0.0%7CChromium%3B120.0.6099.109%7CHeadlessChrome%3B120.0.6099.109&uamb=0&uam=&uap=Linux&uapv=6.2.0&uaw=0&_s=1&sid=1703621857&sct=1&seg=0&dl=https%3A%2F%2Fmarketingisbs.marketing%2F&dt=Hello%20there&en=page_view&_fv=1&_nsi=1&_ss=1&_ee=1&tfd=915"}, "requestId": "19186.17", "timestamp": 3046.840681, "type": "Ping", "wallTime": 1703621857.500542},{"documentURL": "https://marketingisbs.marketing/", "frameId": "6ABFA60F277AEB7D86AD858E7D73D2FE", "hasUserGesture": false, "initiator": {"stack": {"callFrames": [{"columnNumber": 45, "functionName": "Uc", "lineNumber": 195, "scriptId": "9", "url": "https://www.googletagmanager.com/gtag/js?id=G-TXTTC83R0T"}, {"columnNumber": 494, "functionName": "JF", "lineNumber": 599, "scriptId": "9", "url": "https://www.googletagmanager.com/gtag/js?id=G-TXTTC83R0T"}, {"columnNumber": 120, "functionName": "LF", "lineNumber": 596, "scriptId": "9", "url": "https://www.googletagmanager.com/gtag/js?id=G-TXTTC83R0T"}, {"columnNumber": 470, "functionName": "MF.D", "lineNumber": 598, "scriptId": "9", "url": "https://www.googletagmanager.com/gtag/js?id=G-TXTTC83R0T"}, {"columnNumber": 78, "functionName": "MF.add", "lineNumber": 599, "scriptId": "9", "url": "https://www.googletagmanager.com/gtag/js?id=G-TXTTC83R0T"}, {"columnNumber": 334, "functionName": "aa.mj", "lineNumber": 619, "scriptId": "9", "url": "https://www.googletagmanager.com/gtag/js?id=G-TXTTC83R0T"}, {"columnNumber": 254, "functionName": "aa.Km", "lineNumber": 619, "scriptId": "9", "url": "https://www.googletagmanager.com/gtag/js?id=G-TXTTC83R0T"}, {"columnNumber": 120, "functionName": "", "lineNumber": 603, "scriptId": "9", "url": "https://www.googletagmanager.com/gtag/js?id=G-TXTTC83R0T"}, {"columnNumber": 340, "functionName": "Qj", "lineNumber": 317, "scriptId": "9", "url": "https://www.googletagmanager.com/gtag/js?id=G-TXTTC83R0T"}, {"columnNumber": 347, "functionName": "dk", "lineNumber": 320, "scriptId": "9", "url": "https://www.googletagmanager.com/gtag/js?id=G-TXTTC83R0T"}, {"columnNumber": 104, "functionName": "k", "lineNumber": 603, "scriptId": "9", "url": "https://www.googletagmanager.com/gtag/js?id=G-TXTTC83R0T"}, {"columnNumber": 167, "functionName": "c", "lineNumber": 367, "scriptId": "9", "url": "https://www.googletagmanager.com/gtag/js?id=G-TXTTC83R0T"}, {"columnNumber": 198, "functionName": "yn", "lineNumber": 367, "scriptId": "9", "url": "https://www.googletagmanager.com/gtag/js?id=G-TXTTC83R0T"}, {"columnNumber": 143, "functionName": "aa.Jm", "lineNumber": 603, "scriptId": "9", "url": "https://www.googletagmanager.com/gtag/js?id=G-TXTTC83R0T"}, {"columnNumber": 677, "functionName": "c", "lineNumber": 622, "scriptId": "9", "url": "https://www.googletagmanager.com/gtag/js?id=G-TXTTC83R0T"}, {"columnNumber": 297, "functionName": "nq", "lineNumber": 408, "scriptId": "9", "url": "https://www.googletagmanager.com/gtag/js?id=G-TXTTC83R0T"}, {"columnNumber": 94, "functionName": "mq.flush", "lineNumber": 411, "scriptId": "9", "url": "https://www.googletagmanager.com/gtag/js?id=G-TXTTC83R0T"}, {"columnNumber": 206, "functionName": "mq.push", "lineNumber": 409, "scriptId": "9", "url": "https://www.googletagmanager.com/gtag/js?id=G-TXTTC83R0T"}, {"columnNumber": 38, "functionName": "config", "lineNumber": 474, "scriptId": "9", "url": "https://www.googletagmanager.com/gtag/js?id=G-TXTTC83R0T"}, {"columnNumber": 471, "functionName": "Sx", "lineNumber": 485, "scriptId": "9", "url": "https://www.googletagmanager.com/gtag/js?id=G-TXTTC83R0T"}, {"columnNumber": 314, "functionName": "Wx.b.push", "lineNumber": 490, "scriptId": "9", "url": "https://www.googletagmanager.com/gtag/js?id=G-TXTTC83R0T"}, {"columnNumber": 302, "functionName": "", "lineNumber": 406, "scriptId": "8", "url": "https://www.googletagmanager.com/gtm.js?id=GTM-NCZZ2T3Z"}]}, "type": "script"}, "loaderId": "BC682C64B0D5F02E31CE5EA697E84EEA", "redirectHasExtraInfo": false, "request": {"hasPostData": true, "headers": {"Referer": "https://marketingisbs.marketing/", "User-Agent": "Mozilla/5.0 (X11; Linux x86_64) AppleWebKit/537.36 (KHTML, like Gecko) HeadlessChrome/120.0.6099.109 Safari/537.36", "sec-ch-ua": "\"Not_A Brand\";v=\"8\", \"Chromium\";v=\"120\", \"HeadlessChrome\";v=\"120\"", "sec-ch-ua-mobile": "?0", "sec-ch-ua-platform": "\"Linux\""}, "initialPriority": "VeryLow", "isSameSite": false, "method": "POST", "mixedContentType": "none", "postDataEntries": [{"bytes": ""}], "referrerPolicy": "strict-origin-when-cross-origin", "url": "https://stats.g.doubleclick.net/g/collect?v=2&tid=G-TXTTC83R0T&cid=1381979668.1703621857&gtm=45je3bt0v9169951526&aip=1&dma=0&gcd=11l1l1l1l1"}, "requestId": "19186.18", "timestamp": 3046.842681, "type": "Ping", "wallTime": 1703621857.501063},{"documentURL": "https://marketingisbs.marketing/", "frameId": "6ABFA60F277AEB7D86AD858E7D73D2FE", "hasUserGesture": false, "initiator": {"columnNumber": 1, "lineNumber": 162, "type": "parser", "url": "https://marketingisbs.marketing/"}, "loaderId": "BC682C64B0D5F02E31CE5EA697E84EEA", "redirectHasExtraInfo": false, "request": {"headers": {"Referer": "https://marketingisbs.marketing/", "User-Agent": "Mozilla/5.0 (X11; Linux x86_64) AppleWebKit/537.36 (KHTML, like Gecko) HeadlessChrome/120.0.6099.109 Safari/537.36", "sec-ch-ua": "\"Not_A Brand\";v=\"8\", \"Chromium\";v=\"120\", \"HeadlessChrome\";v=\"120\"", "sec-ch-ua-mobile": "?0", "sec-ch-ua-platform": "\"Linux\""}, "initialPriority": "Low", "isSameSite": false, "method": "GET", "mixedContentType": "none", "referrerPolicy": "strict-origin-when-cross-origin", "url": "https://googleads.g.doubleclick.net/pagead/viewthroughconversion/marketingisbs.marketing/?random=1679098064&cv=11&fst=1703621857426&bg=ffffff&guid=ON&async=1&gtm=45He3bt0v9168766396&gcd=11l1l1l1l1&dma=0&u_w=800&u_h=600&url=https%3A%2F%2Fmarketingisbs.marketing%2F&label=marketingisbs.marketing&hn=www.googleadservices.com&frm=0&tiba=Hello%20there&value=0&auid=577895664.1703621857&uaa=x86&uab=64&uafvl=Not_A%2520Brand%3B8.0.0.0%7CChromium%3B120.0.6099.109%7CHeadlessChrome%3B120.0.6099.109&uamb=0&uap=Linux&uapv=6.2.0&uaw=0&fmt=3&ct_cookie_present=false&ocp_id=4TSLZafTHMucoPMPhv-MkAU&sscte=1&crd=&eitems=ChAIgJCqrAYQpJCk2cHFzo4IEh0AqZEZfNRNJ231ETSYfLmrbn764QWMQBhOvdDVIA&pscrd=EkxDaEFJZ0pDcXJBWVE3OUs4MnBURXN2WUhFaVVBdHp6YmpVWUxSejFHZG03ZG9McjFiM0dybEJkblNVVW8tbzFSWGVFQVoyemg3ZDFVGldDaEFJZ0pDcXJBWVFwcks0cjkyNjVkRVVFaTBBamdqR0owS21sd3J0djJCUUlNQTFxYU9yY0lsLWNNYVRFbkpmbDhxcVJDalVsZWpwSDhDMTFXYmVVbHciEwjnx5X99a2DAxVLDmgIHYY_A1I"}, "requestId": "19186.19", "timestamp": 3046.860803, "type": "Image", "wallTime": 1703621857.519053},{"documentURL": "https://marketingisbs.marketing/", "frameId": "6ABFA60F277AEB7D86AD858E7D73D2FE", "hasUserGesture": false, "initiator": {"columnNumber": 1, "lineNumber": 162, "type": "parser", "url": "https://marketingisbs.marketing/"}, "loaderId": "BC682C64B0D5F02E31CE5EA697E84EEA", "redirectHasExtraInfo": true, "redirectResponse": {"alternateProtocolUsage": "unspecifiedReason", "connectionId": 123, "connectionReused": false, "encodedDataLength": 1230, "fromDiskCache": false, "fromPrefetchCache": false, "fromServiceWorker": false, "headers": {"alt-svc": "h3=\":443\"; ma=2592000,h3-29=\":443\"; ma=2592000", "cache-control": "no-cache, must-revalidate", "content-length": "42", "content-type": "image/gif", "cross-origin-resource-policy": "cross-origin", "date": "Tue, 26 Dec 2023 20:17:37 GMT", "expires": "Fri, 01 Jan 1990 00:00:00 GMT", "location": "https://www.google.com/pagead/1p-conversion/marketingisbs.marketing/?random=1679098064&cv=11&fst=1703621857426&bg=ffffff&guid=ON&async=1&gtm=45He3bt0v9168766396&gcd=11l1l1l1l1&dma=0&u_w=800&u_h=600&url=https%3A%2F%2Fmarketingisbs.marketing%2F&label=marketingisbs.marketing&hn=www.googleadservices.com&frm=0&tiba=Hello%20there&value=0&auid=577895664.1703621857&uaa=x86&uab=64&uafvl=Not_A%2520Brand%3B8.0.0.0%7CChromium%3B120.0.6099.109%7CHeadlessChrome%3B120.0.6099.109&uamb=0&uap=Linux&uapv=6.2.0&uaw=0&fmt=3&ct_cookie_present=false&sscte=1&crd=&pscrd=EkxDaEFJZ0pDcXJBWVE3OUs4MnBURXN2WUhFaVVBdHp6YmpVWUxSejFHZG03ZG9McjFiM0dybEJkblNVVW8tbzFSWGVFQVoyemg3ZDFVGldDaEFJZ0pDcXJBWVFwcks0cjkyNjVkRVVFaTBBamdqR0owS21sd3J0djJCUUlNQTFxYU9yY0lsLWNNYVRFbkpmbDhxcVJDalVsZWpwSDhDMTFXYmVVbHciEwjnx5X99a2DAxVLDmgIHYY_A1I&is_vtc=1&ocp_id=4TSLZafTHMucoPMPhv-MkAU&cid=CAQSGwAvHhf_R3OWw3BRNUvoz-Ps2t_mrYgZV8tHGA&eitems=ChAIgJCqrAYQpJCk2cHFzo4IEh0AqZEZfMfMkWFhwr5xhL39rCT_Jc0-LJ9r1K-wNw&random=1131495435", "p3p": "policyref=\"https://googleads.g.doubleclick.net/pagead/gcn_p3p_.xml\", CP=\"CURa ADMa DEVa TAIo PSAo PSDo OUR IND UNI PUR INT DEM STA PRE COM NAV OTC NOI DSP COR\"", "pragma": "no-cache", "server": "cafe", "timing-allow-origin": "*", "x-content-type-options": "nosniff", "x-xss-protection": "0"}, "mimeType": "image/gif", "protocol": "h2", "remoteIPAddress": "142.250.31.156", "remotePort": 443, "responseTime": 1703621857543.922, "securityDetails": {"certificateId": 0, "certificateTransparencyCompliance": "unknown", "cipher": "AES_128_GCM", "encryptedClientHello": false, "issuer": "GTS CA 1C3", "keyExchange": "", "keyExchangeGroup": "X25519", "protocol": "TLS 1.3", "sanList": ["*.g.doubleclick.net", "*.invitemedia.com", "g.doubleclick.net", "googleadservices.com", "*.googleadservices.com", "googlesyndication.com", "*.googlesyndication.com", "*.safeframe.googlesyndication.com", "googletagservices.com", "*.googletagservices.com", "media.admob.com"], "serverSignatureAlgorithm": 1027, "signedCertificateTimestampList": [], "subjectName": "*.g.doubleclick.net", "validFrom": 1700467370, "validTo": 1707724969}, "securityState": "secure", "status": 302, "statusText": "", "timing": {"connectEnd": 8.309, "connectStart": 1.835, "dnsEnd": 1.835, "dnsStart": 1.829, "proxyEnd": -1, "proxyStart": -1, "pushEnd": 0, "pushStart": 0, "receiveHeadersEnd": 24.298, "receiveHeadersStart": 24.186, "requestTime": 3046.861477, "sendEnd": 8.473, "sendStart": 8.401, "sslEnd": 8.307, "sslStart": 3.881, "workerFetchStart": -1, "workerReady": -1, "workerRespondWithSettled": -1, "workerStart": -1}, "url": "https://googleads.g.doubleclick.net/pagead/viewthroughconversion/marketingisbs.marketing/?random=1679098064&cv=11&fst=1703621857426&bg=ffffff&guid=ON&async=1&gtm=45He3bt0v9168766396&gcd=11l1l1l1l1&dma=0&u_w=800&u_h=600&url=https%3A%2F%2Fmarketingisbs.marketing%2F&label=marketingisbs.marketing&hn=www.googleadservices.com&frm=0&tiba=Hello%20there&value=0&auid=577895664.1703621857&uaa=x86&uab=64&uafvl=Not_A%2520Brand%3B8.0.0.0%7CChromium%3B120.0.6099.109%7CHeadlessChrome%3B120.0.6099.109&uamb=0&uap=Linux&uapv=6.2.0&uaw=0&fmt=3&ct_cookie_present=false&ocp_id=4TSLZafTHMucoPMPhv-MkAU&sscte=1&crd=&eitems=ChAIgJCqrAYQpJCk2cHFzo4IEh0AqZEZfNRNJ231ETSYfLmrbn764QWMQBhOvdDVIA&pscrd=EkxDaEFJZ0pDcXJBWVE3OUs4MnBURXN2WUhFaVVBdHp6YmpVWUxSejFHZG03ZG9McjFiM0dybEJkblNVVW8tbzFSWGVFQVoyemg3ZDFVGldDaEFJZ0pDcXJBWVFwcks0cjkyNjVkRVVFaTBBamdqR0owS21sd3J0djJCUUlNQTFxYU9yY0lsLWNNYVRFbkpmbDhxcVJDalVsZWpwSDhDMTFXYmVVbHciEwjnx5X99a2DAxVLDmgIHYY_A1I"}, "request": {"headers": {"Referer": "https://marketingisbs.marketing/", "User-Agent": "Mozilla/5.0 (X11; Linux x86_64) AppleWebKit/537.36 (KHTML, like Gecko) HeadlessChrome/120.0.6099.109 Safari/537.36"}, "initialPriority": "Low", "isSameSite": false, "method": "GET", "mixedContentType": "none", "referrerPolicy": "strict-origin-when-cross-origin", "url": "https://www.google.com/pagead/1p-conversion/marketingisbs.marketing/?random=1679098064&cv=11&fst=1703621857426&bg=ffffff&guid=ON&async=1&gtm=45He3bt0v9168766396&gcd=11l1l1l1l1&dma=0&u_w=800&u_h=600&url=https%3A%2F%2Fmarketingisbs.marketing%2F&label=marketingisbs.marketing&hn=www.googleadservices.com&frm=0&tiba=Hello%20there&value=0&auid=577895664.1703621857&uaa=x86&uab=64&uafvl=Not_A%2520Brand%3B8.0.0.0%7CChromium%3B120.0.6099.109%7CHeadlessChrome%3B120.0.6099.109&uamb=0&uap=Linux&uapv=6.2.0&uaw=0&fmt=3&ct_cookie_present=false&sscte=1&crd=&pscrd=EkxDaEFJZ0pDcXJBWVE3OUs4MnBURXN2WUhFaVVBdHp6YmpVWUxSejFHZG03ZG9McjFiM0dybEJkblNVVW8tbzFSWGVFQVoyemg3ZDFVGldDaEFJZ0pDcXJBWVFwcks0cjkyNjVkRVVFaTBBamdqR0owS21sd3J0djJCUUlNQTFxYU9yY0lsLWNNYVRFbkpmbDhxcVJDalVsZWpwSDhDMTFXYmVVbHciEwjnx5X99a2DAxVLDmgIHYY_A1I&is_vtc=1&ocp_id=4TSLZafTHMucoPMPhv-MkAU&cid=CAQSGwAvHhf_R3OWw3BRNUvoz-Ps2t_mrYgZV8tHGA&eitems=ChAIgJCqrAYQpJCk2cHFzo4IEh0AqZEZfMfMkWFhwr5xhL39rCT_Jc0-LJ9r1K-wNw&random=1131495435"}, "requestId": "19186.19", "timestamp": 3046.886456, "type": "Image", "wallTime": 1703621857.544715},{}]